{"last_updated":"2026-02-27 09:28:14 UTC","summary":{"total":603,"open":21,"closed":582,"res_pct":96.5,"avg_tat":"4h 53m"},"agents":[{"name":"Manoj Chauhan","total":173,"open":5,"closed":168,"res_pct":97.1,"avg_tat_mins":367,"avg_tat":"6h 7m","psat_pct":81.0,"psat_n":21,"grade":"B","daily":[{"date":"2026-02-26","total":21,"closed":21,"res_pct":100.0,"avg_tat":"2h 8m"},{"date":"2026-02-25","total":14,"closed":14,"res_pct":100.0,"avg_tat":"24m"},{"date":"2026-02-24","total":54,"closed":52,"res_pct":96.3,"avg_tat":"7h 40m"},{"date":"2026-02-23","total":46,"closed":44,"res_pct":95.7,"avg_tat":"7h 26m"},{"date":"2026-02-22","total":38,"closed":37,"res_pct":97.4,"avg_tat":"6h 17m"}]},{"name":"Irshad Ahmad","total":154,"open":0,"closed":154,"res_pct":100.0,"avg_tat_mins":218,"avg_tat":"3h 38m","psat_pct":47.4,"psat_n":19,"grade":"E","daily":[{"date":"2026-02-26","total":11,"closed":11,"res_pct":100.0,"avg_tat":"36m"},{"date":"2026-02-25","total":23,"closed":23,"res_pct":100.0,"avg_tat":"1h 7m"},{"date":"2026-02-24","total":43,"closed":43,"res_pct":100.0,"avg_tat":"1h 49m"},{"date":"2026-02-23","total":39,"closed":39,"res_pct":100.0,"avg_tat":"3h 23m"},{"date":"2026-02-22","total":38,"closed":38,"res_pct":100.0,"avg_tat":"8h 13m"}]},{"name":"Umesh Goswami PTL","total":113,"open":2,"closed":111,"res_pct":98.2,"avg_tat_mins":376,"avg_tat":"6h 16m","psat_pct":85.7,"psat_n":7,"grade":"B","daily":[{"date":"2026-02-26","total":5,"closed":3,"res_pct":60.0,"avg_tat":"1h 54m"},{"date":"2026-02-25","total":3,"closed":3,"res_pct":100.0,"avg_tat":"22m"},{"date":"2026-02-24","total":34,"closed":34,"res_pct":100.0,"avg_tat":"6h 59m"},{"date":"2026-02-23","total":31,"closed":31,"res_pct":100.0,"avg_tat":"6h 39m"},{"date":"2026-02-22","total":40,"closed":40,"res_pct":100.0,"avg_tat":"6h 6m"}]},{"name":"Ankit kumar PTL","total":37,"open":4,"closed":33,"res_pct":89.2,"avg_tat_mins":429,"avg_tat":"7h 9m","psat_pct":50.0,"psat_n":10,"grade":"E","daily":[{"date":"2026-02-26","total":21,"closed":20,"res_pct":95.2,"avg_tat":"55m"},{"date":"2026-02-25","total":14,"closed":12,"res_pct":85.7,"avg_tat":"6h 8m"},{"date":"2026-02-24","total":1,"closed":0,"res_pct":0.0,"avg_tat":"\u2014"},{"date":"2026-02-22","total":1,"closed":1,"res_pct":100.0,"avg_tat":"4d 22h"}]},{"name":"Arvind Diwakar PTL","total":31,"open":8,"closed":23,"res_pct":74.2,"avg_tat_mins":86,"avg_tat":"1h 26m","psat_pct":100.0,"psat_n":1,"grade":"A","daily":[{"date":"2026-02-26","total":27,"closed":23,"res_pct":85.2,"avg_tat":"1h 26m"},{"date":"2026-02-25","total":1,"closed":0,"res_pct":0.0,"avg_tat":"\u2014"},{"date":"2026-02-24","total":1,"closed":0,"res_pct":0.0,"avg_tat":"\u2014"},{"date":"2026-02-23","total":1,"closed":0,"res_pct":0.0,"avg_tat":"\u2014"},{"date":"2026-02-22","total":1,"closed":0,"res_pct":0.0,"avg_tat":"\u2014"}]},{"name":"HAMMAD SIDDIQUI  Wiom","total":22,"open":2,"closed":20,"res_pct":90.9,"avg_tat_mins":409,"avg_tat":"6h 49m","psat_pct":100.0,"psat_n":5,"grade":"A","daily":[{"date":"2026-02-26","total":21,"closed":19,"res_pct":90.5,"avg_tat":"5h 40m"},{"date":"2026-02-25","total":1,"closed":1,"res_pct":100.0,"avg_tat":"1d 3h"}]},{"name":"Jaswant Singh PTL","total":17,"open":0,"closed":17,"res_pct":100.0,"avg_tat_mins":97,"avg_tat":"1h 37m","psat_pct":100.0,"psat_n":3,"grade":"A","daily":[{"date":"2026-02-26","total":17,"closed":17,"res_pct":100.0,"avg_tat":"1h 37m"}]},{"name":"Harish Kumar PTL","total":16,"open":0,"closed":16,"res_pct":100.0,"avg_tat_mins":108,"avg_tat":"1h 48m","psat_pct":null,"psat_n":0,"grade":"N/A","daily":[{"date":"2026-02-24","total":7,"closed":7,"res_pct":100.0,"avg_tat":"41m"},{"date":"2026-02-23","total":5,"closed":5,"res_pct":100.0,"avg_tat":"3h 48m"},{"date":"2026-02-22","total":4,"closed":4,"res_pct":100.0,"avg_tat":"1h 17m"}]},{"name":"Ritik Dubey PTL","total":15,"open":0,"closed":15,"res_pct":100.0,"avg_tat_mins":139,"avg_tat":"2h 19m","psat_pct":75.0,"psat_n":4,"grade":"C","daily":[{"date":"2026-02-25","total":14,"closed":14,"res_pct":100.0,"avg_tat":"46m"},{"date":"2026-02-24","total":1,"closed":1,"res_pct":100.0,"avg_tat":"19h 18m"}]},{"name":"Unassigned","total":13,"open":0,"closed":13,"res_pct":100.0,"avg_tat_mins":57,"avg_tat":"57m","psat_pct":null,"psat_n":0,"grade":"N/A","daily":[{"date":"2026-02-26","total":13,"closed":13,"res_pct":100.0,"avg_tat":"57m"}]},{"name":"Manish Pathak","total":6,"open":0,"closed":6,"res_pct":100.0,"avg_tat_mins":155,"avg_tat":"2h 35m","psat_pct":50.0,"psat_n":2,"grade":"E","daily":[{"date":"2026-02-25","total":4,"closed":4,"res_pct":100.0,"avg_tat":"41m"},{"date":"2026-02-22","total":2,"closed":2,"res_pct":100.0,"avg_tat":"8h 15m"}]},{"name":"Rupesh Diwakar PX","total":3,"open":0,"closed":3,"res_pct":100.0,"avg_tat_mins":15,"avg_tat":"15m","psat_pct":100.0,"psat_n":2,"grade":"A","daily":[{"date":"2026-02-25","total":2,"closed":2,"res_pct":100.0,"avg_tat":"18m"},{"date":"2026-02-23","total":1,"closed":1,"res_pct":100.0,"avg_tat":"10m"}]},{"name":"Inventory Team","total":3,"open":0,"closed":3,"res_pct":100.0,"avg_tat_mins":838,"avg_tat":"13h 58m","psat_pct":0.0,"psat_n":1,"grade":"E","daily":[{"date":"2026-02-25","total":2,"closed":2,"res_pct":100.0,"avg_tat":"8h 24m"},{"date":"2026-02-23","total":1,"closed":1,"res_pct":100.0,"avg_tat":"1d 1h"}]}],"open_tickets":[{"id":"771748882094","agent":"Manoj Chauhan","title":"Wants to Return Pickup Devices","created":"22-02-2026 13:58","date":"2026-02-22","age":"4d 19h","age_mins":6930},{"id":"771769864124","agent":"Arvind Diwakar PTL","title":"Some Other Issue","created":"22-02-2026 19:47","date":"2026-02-22","age":"4d 13h","age_mins":6581},{"id":"771828411334","agent":"Manoj Chauhan","title":"New project ","created":"23-02-2026 12:03","date":"2026-02-23","age":"3d 21h","age_mins":5605},{"id":"771844297088","agent":"Arvind Diwakar PTL","title":"partner bol rhe hai ssid update nhi ho rahi hai ","created":"23-02-2026 16:28","date":"2026-02-23","age":"3d 17h","age_mins":5340},{"id":"771846933750","agent":"Manoj Chauhan","title":"PTL-Partner|Customer Internet / Recharge / Account Issues|Customer Recharge Related|Customer Unable to Recharge","created":"23-02-2026 17:12","date":"2026-02-23","age":"3d 16h","age_mins":5296},{"id":"771921580796","agent":"Arvind Diwakar PTL","title":"Wants to Return Pickup Devices","created":"24-02-2026 13:56","date":"2026-02-24","age":"2d 19h","age_mins":4052},{"id":"771930907948","agent":"Ankit kumar PTL","title":"Want to know details of plan","created":"24-02-2026 16:31","date":"2026-02-24","age":"2d 16h","age_mins":3897},{"id":"771933448353","agent":"Manoj Chauhan","title":"service strike rate ","created":"24-02-2026 17:14","date":"2026-02-24","age":"2d 16h","age_mins":3854},{"id":"771936018616","agent":"Manoj Chauhan","title":"Partner ka ka h h ki unka ek cx he jinke saath frode kiya gaya he partner ka ka h h ki wiom ke salsment team thi jinhone cx se recharge karne ke liye apne qr code pe recharge karwa liye he or cx ka recharge nni kiya he ab partner ka kah h ki cx he jo ki wo partner ko devise nhi dege ab jab tak mera payment refund nhi milta ","created":"24-02-2026 17:56","date":"2026-02-24","age":"2d 15h","age_mins":3812},{"id":"772001711623","agent":"Ankit kumar PTL","title":"some other issue ","created":"25-02-2026 12:11","date":"2026-02-25","age":"1d 21h","age_mins":2717},{"id":"772002626105","agent":"Ankit kumar PTL","title":"Unable to transfer the ammount ","created":"25-02-2026 12:27","date":"2026-02-25","age":"1d 21h","age_mins":2701},{"id":"772005716830","agent":"Arvind Diwakar PTL","title":"new project","created":"25-02-2026 13:18","date":"2026-02-25","age":"1d 20h","age_mins":2650},{"id":"772084730505","agent":"Arvind Diwakar PTL","title":"PTL-Partner|Sales / Enquiries / Information|Business Related|New Project","created":"26-02-2026 11:15","date":"2026-02-26","age":"22h 13m","age_mins":1333},{"id":"772085302930","agent":"Arvind Diwakar PTL","title":"Recharge commision issue ","created":"26-02-2026 11:25","date":"2026-02-26","age":"22h 3m","age_mins":1323},{"id":"772088093101","agent":"Umesh Goswami PTL","title":"Wrong Ticket Generate","created":"26-02-2026 12:11","date":"2026-02-26","age":"21h 17m","age_mins":1277},{"id":"772089954322","agent":"HAMMAD SIDDIQUI  Wiom","title":"PTL-Partner|Some Other Issue|Some Other Issue|Some Other Issue","created":"26-02-2026 12:42","date":"2026-02-26","age":"20h 46m","age_mins":1246},{"id":"772097474451","agent":"Arvind Diwakar PTL","title":"calling","created":"26-02-2026 14:47","date":"2026-02-26","age":"18h 41m","age_mins":1121},{"id":"772098495800","agent":"Arvind Diwakar PTL","title":"rohit lottery","created":"26-02-2026 15:04","date":"2026-02-26","age":"18h 24m","age_mins":1104},{"id":"772100699293","agent":"Ankit kumar PTL","title":"Some Other Issue","created":"26-02-2026 15:41","date":"2026-02-26","age":"17h 47m","age_mins":1067},{"id":"772109690570","agent":"HAMMAD SIDDIQUI  Wiom","title":"PTL-Partner|Sales / Enquiries / Information|Business Related|New Project","created":"26-02-2026 18:11","date":"2026-02-26","age":"15h 17m","age_mins":917},{"id":"772118093642","agent":"Umesh Goswami PTL","title":"Some Other Issue","created":"26-02-2026 20:31","date":"2026-02-26","age":"12h 57m","age_mins":777}]}